coarseclassevaluator.py
coarseclassevaluator-1.1.dist-info/LICENSE.txt
coarseclassevaluator-1.1.dist-info/METADATA
coarseclassevaluator-1.1.dist-info/WHEEL
coarseclassevaluator-1.1.dist-info/top_level.txt
coarseclassevaluator-1.1.dist-info/RECORD
