Metadata-Version: 2.1
Name: coarseclassevaluator
Version: 1.1
Summary: CoarseClassvisual formulator
Home-page: UNKNOWN
Author: Asheesh Janda
Author-email: asheesh.janda.ds@gmail.com
License: UNKNOWN
Project-URL: Source, https://github.com/AsheeshJandaDS/coarseclassvisual
Project-URL: Tracker, https://github.com/AsheeshJandaDS/coarseclassvisual/issues
Platform: UNKNOWN
Classifier: Programming Language :: Python :: 3
Classifier: License :: OSI Approved :: MIT License
Classifier: Operating System :: OS Independent
Requires-Python: >=3.6
License-File: LICENSE.txt
